.gitignore
CHANGES.rst
LICENSE.txt
Makefile
README.rst
setup.py
Basket.egg-info/PKG-INFO
Basket.egg-info/SOURCES.txt
Basket.egg-info/dependency_links.txt
Basket.egg-info/entry_points.txt
Basket.egg-info/not-zip-safe
Basket.egg-info/top_level.txt
basket/__init__.py
basket/main.py
basket/tests/__init__.py
basket/tests/shelltest.py
basket/tests/test_doc.py
basket/tests/test_main.py
basket/tests/usage.rst
docs/bg.png
docs/index.html
docs/main.css