Metadata-Version: 1.0
Name: Basket
Version: 0.9
Summary: A local static PyPI repository builder
Home-page: http://packages.python.org/Basket
Author: Damien Baty
Author-email: damien.baty.remove@gmail.com
License: UNKNOWN
Keywords: eggs easy_install pip package static repository pypi
Platform: UNKNOWN
Classifier: Development Status :: 4 - Beta
Classifier: Environment :: Console
Classifier: License :: OSI Approved :: BSD License
Classifier: Programming Language :: Python :: 2.7
Classifier: Topic :: System :: Software Distribution
